blagues_api/__init__.py
blagues_api/main.py
blagues_api-1.0.3.dist-info/LICENSE
blagues_api-1.0.3.dist-info/METADATA
blagues_api-1.0.3.dist-info/WHEEL
blagues_api-1.0.3.dist-info/RECORD
