Metadata-Version: 2.1
Name: blagues_api
Version: 1.0.3
Summary: Official client for Blagues API
Home-page: https://www.blagues-api.fr/
License: MIT
Author: baptiste0928
Author-email: contact@baptiste0928.net
Requires-Python: >=3.8,<4.0
Classifier: License :: OSI Approved :: MIT License
Classifier: Programming Language :: Python :: 3
Classifier: Programming Language :: Python :: 3.8
Classifier: Programming Language :: Python :: 3.9
Classifier: Programming Language :: Python :: 3.10
Classifier: Programming Language :: Python :: 3.11
Classifier: Programming Language :: Python :: 3.12
Requires-Dist: aiohttp (>=3.7,<4.0)
Requires-Dist: pydantic (>=1.8,<2.0)
Project-URL: Repository, https://github.com/Blagues-API/package-py
